adaptor/__init__.py
adaptor/adapter.py
adaptor/lang_module.py
adaptor/schedules.py
adaptor/utils.py
adaptor/evaluators/__init__.py
adaptor/evaluators/evaluator_base.py
adaptor/evaluators/generative.py
adaptor/evaluators/prism.py
adaptor/evaluators/question_answering.py
adaptor/evaluators/sequence_classification.py
adaptor/evaluators/token_classification.py
adaptor/objectives/CLM.py
adaptor/objectives/MLM.py
adaptor/objectives/__init__.py
adaptor/objectives/backtranslation.py
adaptor/objectives/classification.py
adaptor/objectives/denoising.py
adaptor/objectives/distillation.py
adaptor/objectives/objective_base.py
adaptor/objectives/question_answering.py
adaptor/objectives/seq2seq.py
adaptor-0.2.5.dist-info/LICENSE
adaptor-0.2.5.dist-info/METADATA
adaptor-0.2.5.dist-info/WHEEL
adaptor-0.2.5.dist-info/top_level.txt
adaptor-0.2.5.dist-info/zip-safe
adaptor-0.2.5.dist-info/RECORD
