Metadata-Version: 2.1
Name: adaptor
Version: 0.2.5
Summary: Adaptor: Objective-centric Adaptation Framework for Language Models.
Home-page: https://github.com/gaussalgo/adaptor
Author: Michal Stefanik & Adaptor Authors & Contributors
Author-email: stefanik.m@mail.muni.cz
License: MIT
Classifier: Intended Audience :: Developers
Classifier: Intended Audience :: Education
Classifier: Intended Audience :: Science/Research
Classifier: Topic :: Scientific/Engineering :: Artificial Intelligence
Classifier: Programming Language :: Python :: 3.8
Requires-Python: >=3.7
License-File: LICENSE
Requires-Dist: torch>=1.7
Requires-Dist: transformers<=4.30.2
Requires-Dist: sentencepiece
Requires-Dist: accelerate>=0.20.1
Requires-Dist: peft<0.13.0,>=0.10.0
Requires-Dist: prefetch-generator>=1.0.3
Requires-Dist: numpy<1.24
Provides-Extra: examples
Requires-Dist: comet-ml; extra == "examples"
Provides-Extra: generative
Requires-Dist: sacrebleu; extra == "generative"
Requires-Dist: rouge-score; extra == "generative"
Requires-Dist: bert-score; extra == "generative"
Requires-Dist: fairseq; extra == "generative"
Requires-Dist: protobuf<=3.20.1; extra == "generative"
